Metadata-Version: 2.1
Name: cs46-trees-colinmulligan
Version: 1.0.0
Summary: cs46 -- assignments 10-12
Home-page: https://github.com/colinmulligan/trees
Author: Colin Mulligan
Author-email: cgmi2015@pomona.edu
License: GPL
Platform: UNKNOWN
Classifier: Programming Language :: Python :: 3
Classifier: Programming Language :: Python :: 3.7
Requires-Dist: pytest
Requires-Dist: hypothesis
Requires-Dist: attrs
